ros_rosidl_typesupport_interface-4.9.5.data/data/include/rosidl_typesupport_interface/rosidl_typesupport_interface/macros.h
ros_rosidl_typesupport_interface-4.9.5.data/data/share/ament_index/resource_index/package_run_dependencies/rosidl_typesupport_interface
ros_rosidl_typesupport_interface-4.9.5.data/data/share/ament_index/resource_index/packages/rosidl_typesupport_interface
ros_rosidl_typesupport_interface-4.9.5.data/data/share/ament_index/resource_index/parent_prefix_path/rosidl_typesupport_interface
ros_rosidl_typesupport_interface-4.9.5.data/data/share/rosidl_typesupport_interface/local_setup.bash
ros_rosidl_typesupport_interface-4.9.5.data/data/share/rosidl_typesupport_interface/local_setup.dsv
ros_rosidl_typesupport_interface-4.9.5.data/data/share/rosidl_typesupport_interface/local_setup.sh
ros_rosidl_typesupport_interface-4.9.5.data/data/share/rosidl_typesupport_interface/local_setup.zsh
ros_rosidl_typesupport_interface-4.9.5.data/data/share/rosidl_typesupport_interface/package.dsv
ros_rosidl_typesupport_interface-4.9.5.data/data/share/rosidl_typesupport_interface/package.xml
ros_rosidl_typesupport_interface-4.9.5.data/data/share/rosidl_typesupport_interface/cmake/ament_cmake_export_include_directories-extras.cmake
ros_rosidl_typesupport_interface-4.9.5.data/data/share/rosidl_typesupport_interface/cmake/ament_cmake_export_targets-extras.cmake
ros_rosidl_typesupport_interface-4.9.5.data/data/share/rosidl_typesupport_interface/cmake/rosidl_typesupport_interfaceConfig-version.cmake
ros_rosidl_typesupport_interface-4.9.5.data/data/share/rosidl_typesupport_interface/cmake/rosidl_typesupport_interfaceConfig.cmake
ros_rosidl_typesupport_interface-4.9.5.data/data/share/rosidl_typesupport_interface/cmake/rosidl_typesupport_interfaceExport.cmake
ros_rosidl_typesupport_interface-4.9.5.data/data/share/rosidl_typesupport_interface/environment/ament_prefix_path.dsv
ros_rosidl_typesupport_interface-4.9.5.dist-info/METADATA
ros_rosidl_typesupport_interface-4.9.5.dist-info/WHEEL
ros_rosidl_typesupport_interface-4.9.5.dist-info/top_level.txt
ros_rosidl_typesupport_interface-4.9.5.dist-info/RECORD
