Metadata-Version: 2.4
Name: ros-rosidl-typesupport-interface
Version: 4.9.5
Summary: A ROS package providing C/C++ macros to define the rosidl typesupport interface.
Dynamic: description
Dynamic: description-content-type
Dynamic: summary
